historical_geocoder/__init__.py
historical_geocoder/calculator.py
historical_geocoder/detector.py
historical_geocoder/extractor.py
historical_geocoder/geocoder.py
historical_geocoder/matcher.py
historical_geocoder/normalizer.py
historical_geocoder/data/2020China.geojson
historical_geocoder/data/2020ChinaCountyTable.csv
historical_geocoder/data/direction.json
historical_geocoder/data/minority_list.txt
historical_geocoder/utils/__init__.py
historical_geocoder/utils/calculation/__init__.py
historical_geocoder/utils/calculation/polygon_to_point.py
historical_geocoder/utils/detection/__init__.py
historical_geocoder/utils/detection/direction_detection_ch.py
historical_geocoder/utils/extraction/__init__.py
historical_geocoder/utils/extraction/chatgpt_extractor.py
historical_geocoder/utils/matching/__init__.py
historical_geocoder/utils/matching/hierarchical_matching_ch.py
historical_geocoder/utils/normalization/__init__.py
historical_geocoder/utils/normalization/normalization_ch.py
historical_geocoder-0.1.11.dist-info/LICENSE
historical_geocoder-0.1.11.dist-info/METADATA
historical_geocoder-0.1.11.dist-info/WHEEL
historical_geocoder-0.1.11.dist-info/top_level.txt
historical_geocoder-0.1.11.dist-info/RECORD
