Metadata-Version: 2.1
Name: historical-geocoder
Version: 0.1.11
Summary: A library to extract historical toponyms and locations from texts, geocode the locations, and visualize the results.
Author: Yuqi Chen
Author-email: cyq0722@pku.edu.cn
License-File: LICENSE
Requires-Dist: geopandas
Requires-Dist: geopy
Requires-Dist: shapely
Requires-Dist: openai
Requires-Dist: keplergl
Requires-Dist: setuptools
